sgbridge/__init__.py
sgbridge/bid.py
sgbridge/bridge.py
sgbridge/card.py
sgbridge/datastore.py
sgbridge/entity.py
sgbridge/exception.py
sgbridge/game.py
sgbridge/player.py
sgbridge-0.0.0.dist-info/LICENSE
sgbridge-0.0.0.dist-info/METADATA
sgbridge-0.0.0.dist-info/WHEEL
sgbridge-0.0.0.dist-info/top_level.txt
sgbridge-0.0.0.dist-info/RECORD
