Metadata-Version: 2.2
Name: sgbridge
Version: 0.0.0
Summary: sgbridge is a package for playing contract bridge with hidden partner!
Home-page: https://github.com/papillonbee/sgbridge
Author: Papan Yongmalwong
Author-email: papillonbee@gmail.com
Classifier: Programming Language :: Python :: 3
Classifier: License :: OSI Approved :: MIT License
Classifier: Operating System :: OS Independent
Requires-Python: >=3.9
License-File: LICENSE
Dynamic: author
Dynamic: author-email
Dynamic: classifier
Dynamic: description
Dynamic: description-content-type
Dynamic: home-page
Dynamic: requires-python
Dynamic: summary
